{
  "extension_name": "biomejs.biome",
  "display_name": "Biome",
  "short_description": "Toolchain of the web",
  "latest_version": "2025.2.72227",
  "last_updated": "2025-02-07T22:31:26.97Z",
  "version_history": [
    {
      "version": "2025.2.72227",
      "flags": "validated",
      "lastUpdated": "2025-02-07T22:31:26.97Z"
    },
    {
      "version": "2025.2.72121",
      "flags": "validated",
      "lastUpdated": "2025-02-07T21:24:46.587Z"
    },
    {
      "version": "2025.2.61917",
      "flags": "validated",
      "lastUpdated": "2025-02-06T19:21:18.263Z"
    },
    {
      "version": "2025.1.272056",
      "flags": "validated",
      "lastUpdated": "2025-01-27T21:00:28.6Z"
    },
    {
      "version": "2024.12.22126",
      "flags": "validated",
      "lastUpdated": "2024-12-02T21:32:40.17Z"
    },
    {
      "version": "2024.11.301111",
      "flags": "validated",
      "lastUpdated": "2024-11-30T11:15:27.073Z"
    },
    {
      "version": "2024.11.291058",
      "flags": "validated",
      "lastUpdated": "2024-11-29T11:02:37.507Z"
    },
    {
      "version": "2024.11.291004",
      "flags": "validated",
      "lastUpdated": "2024-11-29T10:08:20.43Z"
    },
    {
      "version": "2024.11.211321",
      "flags": "validated",
      "lastUpdated": "2024-11-21T13:26:06.2Z"
    },
    {
      "version": "2024.10.131712",
      "flags": "validated",
      "lastUpdated": "2024-10-13T17:16:15.14Z"
    }
  ],
  "categories": [
    "Linters",
    "Formatters"
  ],
  "tags": [
    "biome_syntax_tree",
    "Formatter",
    "Linter"
  ],
  "download_url": "https://marketplace.visualstudio.com/_apis/public/gallery/publishers/biomejs/vsextensions/biome/2025.2.72227/vspackage",
  "marketplace_url": "https://marketplace.visualstudio.com/items?itemName=biomejs.biome"
}