{
  "extension_name": "wmaurer.change-case",
  "display_name": "change-case",
  "short_description": "Quickly change the case (camelCase, CONSTANT_CASE, snake_case, etc) of the current selection or current word",
  "latest_version": "1.0.0",
  "last_updated": "2016-11-01T20:34:36.183Z",
  "version_history": [
    {
      "version": "1.0.0",
      "flags": "validated",
      "lastUpdated": "2016-11-01T20:34:36.183Z"
    },
    {
      "version": "0.4.1",
      "flags": "validated",
      "lastUpdated": "2016-02-13T21:36:39.907Z"
    },
    {
      "version": "0.4.0",
      "flags": "validated",
      "lastUpdated": "2016-02-13T17:05:04.69Z"
    },
    {
      "version": "0.3.2",
      "flags": "validated",
      "lastUpdated": "2015-12-09T20:24:05.267Z"
    },
    {
      "version": "0.3.1",
      "flags": "validated",
      "lastUpdated": "2015-11-28T09:21:50.443Z"
    },
    {
      "version": "0.3.0",
      "flags": "validated",
      "lastUpdated": "2015-11-28T09:01:10.09Z"
    },
    {
      "version": "0.2.3",
      "flags": "validated",
      "lastUpdated": "2015-11-20T07:33:23.96Z"
    },
    {
      "version": "0.2.2",
      "flags": "validated",
      "lastUpdated": "2015-11-20T07:30:12.52Z"
    },
    {
      "version": "0.2.1",
      "flags": "validated",
      "lastUpdated": "2015-11-18T21:16:59.78Z"
    },
    {
      "version": "0.2.0",
      "flags": "validated",
      "lastUpdated": "2015-11-08T21:03:21.87Z"
    }
  ],
  "categories": [
    "Other"
  ],
  "tags": [],
  "download_url": "https://marketplace.visualstudio.com/_apis/public/gallery/publishers/wmaurer/vsextensions/change-case/1.0.0/vspackage",
  "marketplace_url": "https://marketplace.visualstudio.com/items?itemName=wmaurer.change-case"
}